timeoutcontext/__init__.py
timeoutcontext/_timeout.py
timeoutcontext-1.1.1.dist-info/top_level.txt
timeoutcontext-1.1.1.dist-info/WHEEL
timeoutcontext-1.1.1.dist-info/metadata.json
timeoutcontext-1.1.1.dist-info/RECORD
timeoutcontext-1.1.1.dist-info/METADATA
timeoutcontext-1.1.1.dist-info/DESCRIPTION.rst
