Metadata-Version: 2.0
Name: timeoutcontext
Version: 1.1.1
Summary: A signal based timeout context manager
Home-page: https://github.com/AntoineCezar/timeoutcontext
Author: Antoine Cezar
Author-email: antoine@cezar.fr
License: BSD
Keywords: timeoutcontext
Platform: UNKNOWN
Classifier: Development Status :: 5 - Production/Stable
Classifier: Intended Audience :: Developers
Classifier: License :: OSI Approved :: BSD License
Classifier: Natural Language :: English
Classifier: Programming Language :: Python :: 2.7
Classifier: Programming Language :: Python :: 3
